portcache
