Metadata-Version: 1.0
Name: portcache
Version: 0.3
Summary: A simple cache for port from remote service
Home-page: https://github.com/oneraghavan/portcache
Author: Raghavan
Author-email: oneraghavan@gmail.com
License: MIT
Platform: UNKNOWN
